id_lib/__init__.py
id_lib/id.py
id_lib/version.py
id_lib-0.0.4.dist-info/AUTHORS
id_lib-0.0.4.dist-info/LICENSE
id_lib-0.0.4.dist-info/METADATA
id_lib-0.0.4.dist-info/NOTICE.txt
id_lib-0.0.4.dist-info/WHEEL
id_lib-0.0.4.dist-info/pbr.json
id_lib-0.0.4.dist-info/top_level.txt
id_lib-0.0.4.dist-info/RECORD
