Metadata-Version: 2.1
Name: id-lib
Version: 0.0.4
Summary: Object ID library
Home-page: https://github.com/denismakogon
Author: Denys Makogon
Author-email: lildee1991@gmail.com
License: UNKNOWN
Platform: UNKNOWN
Classifier: Intended Audience :: Information Technology
Classifier: Intended Audience :: System Administrators
Classifier: License :: OSI Approved :: Apache Software License
Classifier: Operating System :: POSIX :: Linux
Classifier: Programming Language :: Python
Classifier: Programming Language :: Python :: 3
Classifier: Programming Language :: Python :: 3.8
Requires-Dist: pbr (==5.4.5)
